[
  {
    "id": 1,
    "name": "Pradhan Mantri Kisan Samman Nidhi (PM-KISAN)",
    "state": "Central",
    "category": "Direct Support",
    "benefit": "₹6,000 per year in three installments.",
    "eligibility": "All landholding farmer families.",
    "documents": "Aadhaar Card, Landholding papers, Bank account details."
  },
  {
    "id": 2,
    "name": "Pradhan Mantri Fasal Bima Yojana (PMFBY)",
    "state": "Central",
    "category": "Insurance",
    "benefit": "Insurance cover against crop failure due to natural calamities.",
    "eligibility": "All farmers who have taken loans or who opt-in.",
    "documents": "Land records, Bank passbook, Aadhaar card."
  },
  {
    "id": 3,
    "name": "Mahatma Jyotirao Phule Shetkari Karjmukti Yojana",
    "state": "Maharashtra",
    "category": "Loan Waiver",
    "benefit": "Loan waiver for farmers with loans up to ₹2 lakh.",
    "eligibility": "Farmers in Maharashtra with specified short-term crop loans.",
    "documents": "Aadhaar Card, Bank loan documents, Ration card."
  },
  {
    "id": 4,
    "name": "Mukhyamantri Krishi Ashirwad Yojana",
    "state": "Jharkhand",
    "category": "Direct Support",
    "benefit": "₹5,000 per acre for farmers with up to 5 acres of land.",
    "eligibility": "Small and marginal farmers of Jharkhand.",
    "documents": "Aadhaar Card, Land records, Bank details."
  },
  {
    "id": 5,
    "name": "Farm Mechanization Scheme",
    "state": "Maharashtra",
    "category": "Machinery",
    "benefit": "Subsidy on purchase of tractors, rotavators, and other farm equipment.",
    "eligibility": "All farmers in Maharashtra.",
    "documents": "Land records (7/12 extract), Aadhaar Card, Quotation of machinery."
  }
]